asynchronize/__init__.py
asynchronize-0.0.1.dist-info/LICENSE
asynchronize-0.0.1.dist-info/METADATA
asynchronize-0.0.1.dist-info/WHEEL
asynchronize-0.0.1.dist-info/top_level.txt
asynchronize-0.0.1.dist-info/RECORD
